_examples/__init__.py
examples/__init__.py
pyfileconf/__init__.py
pyfileconf/batch.py
pyfileconf/debug.py
pyfileconf/interfaces.py
pyfileconf/iterate.py
pyfileconf/main.py
pyfileconf/userbase.py
pyfileconf/assignments/__init__.py
pyfileconf/assignments/logic/__init__.py
pyfileconf/assignments/logic/write.py
pyfileconf/assignments/models/__init__.py
pyfileconf/assignments/models/container.py
pyfileconf/assignments/models/statement.py
pyfileconf/basemodels/__init__.py
pyfileconf/basemodels/collection.py
pyfileconf/basemodels/config.py
pyfileconf/basemodels/container.py
pyfileconf/basemodels/file.py
pyfileconf/basemodels/registrar.py
pyfileconf/config/__init__.py
pyfileconf/config/logic/__init__.py
pyfileconf/config/logic/apply.py
pyfileconf/config/logic/load.py
pyfileconf/config/logic/write.py
pyfileconf/config/models/__init__.py
pyfileconf/config/models/config.py
pyfileconf/config/models/file.py
pyfileconf/config/models/interfaces.py
pyfileconf/config/models/manager.py
pyfileconf/config/models/section.py
pyfileconf/data/__init__.py
pyfileconf/data/logic/__init__.py
pyfileconf/data/logic/convert.py
pyfileconf/data/logic/display.py
pyfileconf/data/logic/merge/__init__.py
pyfileconf/data/logic/merge/display.py
pyfileconf/data/logic/merge/summarize.py
pyfileconf/data/models/__init__.py
pyfileconf/data/models/astitems.py
pyfileconf/data/models/collection.py
pyfileconf/data/models/config.py
pyfileconf/data/models/dictconfig.py
pyfileconf/data/models/dictfile.py
pyfileconf/data/models/file.py
pyfileconf/data/models/registrar.py
pyfileconf/dictfiles/__init__.py
pyfileconf/dictfiles/modify.py
pyfileconf/exceptions/__init__.py
pyfileconf/exceptions/assignments.py
pyfileconf/exceptions/base.py
pyfileconf/exceptions/config.py
pyfileconf/exceptions/imports.py
pyfileconf/exceptions/pipelinemanager.py
pyfileconf/exceptions/registrar.py
pyfileconf/imports/__init__.py
pyfileconf/imports/logic/__init__.py
pyfileconf/imports/logic/load/__init__.py
pyfileconf-0.15.2.dist-info/LICENSE.md
pyfileconf-0.15.2.dist-info/METADATA
pyfileconf-0.15.2.dist-info/WHEEL
pyfileconf-0.15.2.dist-info/entry_points.txt
pyfileconf-0.15.2.dist-info/top_level.txt
pyfileconf-0.15.2.dist-info/RECORD
