Metadata-Version: 2.1
Name: pyfileconf
Version: 0.15.2
Summary: Generate Python configuration files from functions and classes and run them from the command line or Python
Home-page: https://github.com/nickderobertis/py-file-conf
Author: Nick DeRobertis
Author-email: whoopnip@gmail.com
License: MIT
Project-URL: Code, https://github.com/nickderobertis/py-file-conf
Project-URL: Documentation, https://nickderobertis.github.io/py-file-conf
Platform: UNKNOWN
Classifier: Development Status :: 3 - Alpha
Classifier: Intended Audience :: Developers
Classifier: Programming Language :: Python :: 3.6
Classifier: Programming Language :: Python :: 3.7
Requires-Dist: astor
Requires-Dist: mixins
Requires-Dist: pandas
Requires-Dist: pd-utils
Requires-Dist: datacode
Requires-Dist: IPython
Requires-Dist: black
Requires-Dist: pluggy
